BHDataAnalysis/__init__.py
BHDataAnalysis/featureEngineeringFile.py
BHDataAnalysis-1.0.5.dist-info/LICENSE
BHDataAnalysis-1.0.5.dist-info/METADATA
BHDataAnalysis-1.0.5.dist-info/WHEEL
BHDataAnalysis-1.0.5.dist-info/top_level.txt
BHDataAnalysis-1.0.5.dist-info/RECORD
