Metadata-Version: 2.1
Name: BHDataAnalysis
Version: 1.0.5
Summary: Header files for Data Analysis preprocessing methods
Author: Developer - Skanda Chandrashekar
Author-email: skanda.chandrashekar@bakerhughes.com
Keywords: data analysis,preprocessing,methods,headerfiles,python
Classifier: Development Status :: 1 - Planning
Classifier: Intended Audience :: Developers
Classifier: Programming Language :: Python :: 3
Classifier: Operating System :: Unix
Classifier: Operating System :: MacOS :: MacOS X
Classifier: Operating System :: Microsoft :: Windows
License-File: LICENSE
Requires-Dist: spacy
Requires-Dist: nltk
Requires-Dist: pandas
